{
  "$schema": "atlas-config-v1",
  "preset": "generic",
  "organization": "",
  "services": {
    "forgejo": { "local_url": "", "external_url": "", "api_path": "/api/v1" },
    "synapse": { "url": "http://localhost:8001", "enabled": false },
    "authentik": { "url": "", "enabled": false },
    "cloud": { "url": "", "enabled": false },
    "hub": { "local_url": "", "external_url": "" }
  },
  "auth": {
    "admin_groups": ["admins"],
    "dev_groups": ["developers"],
    "user_groups": ["users"]
  },
  "secrets": {
    "provider": "env",
    "vaultwarden_server": ""
  },
  "identity": {
    "co_author_name": "ATLAS AI",
    "co_author_email": ""
  }
}
